xll_kit/__init__.py
xll_kit/dependencies.py
xll_kit/redis_manager.py
xll_kit/version.py
xll_kit/core/__init__.py
xll_kit/core/audit/__init__.py
xll_kit/core/audit/diff.py
xll_kit/core/audit/hooks.py
xll_kit/core/audit/logger.py
xll_kit/core/audit/router.py
xll_kit/core/hooks/__init__.py
xll_kit/core/hooks/decorator.py
xll_kit/core/hooks/loader.py
xll_kit/core/hooks/manager.py
xll_kit/core/hooks/types.py
xll_kit/core/permission/__init__.py
xll_kit/core/permission/registry.py
xll_kit/core/permission/sample.py
xll_kit/cruds/__init__.py
xll_kit/cruds/base.py
xll_kit/cruds/async/__init__.py
xll_kit/cruds/async/base.py
xll_kit/cruds/mixins/__init__.py
xll_kit/cruds/mixins/expand_mixin.py
xll_kit/cruds/mixins/filter_mixin.py
xll_kit/cruds/mixins/soft_delete_mixin.py
xll_kit/cruds/mixins/upsert_mixin.py
xll_kit/database/__init__.py
xll_kit/database/builders.py
xll_kit/database/database_manager.py
xll_kit/database/exceptions.py
xll_kit/database/executor.py
xll_kit/database/repository.py
xll_kit/database/session_manager.py
xll_kit/database/async/__init__.py
xll_kit/database/async/manager.py
xll_kit/models/__init__.py
xll_kit/models/audit_log.py
xll_kit/models/base.py
xll_kit/models/mixins.py
xll_kit/redis/__init__.py
xll_kit/redis/base.py
xll_kit/redis/cache.py
xll_kit/redis/lock.py
xll_kit/redis/manager.py
xll_kit/redis/pubsub.py
xll_kit/repositories/__init__.py
xll_kit/repositories/base.py
xll_kit/schemas/__init__.py
xll_kit/schemas/common.py
xll_kit/schemas/request.py
xll_kit/schemas/response.py
xll_kit/services/__init__.py
xll_kit/services/base.py
xll_kit/services/base_new.py
xll_kit/services/pagination.py
xll_kit/services/mixins/__init__.py
xll_kit/services/mixins/audit_mixin.py
xll_kit/services/mixins/expand_mixin.py
xll_kit/services/mixins/pagination_mixin.py
xll_kit/services/mixins/permission_mixin.py
xll_kit/services/mixins/sort_mixin.py
xll_kit/utils/__init__.py
xll_kit/utils/date_util.py
xll_kit/utils/logger.py
xll_kit/utils/str_util.py
xll_kit-0.1.1.dist-info/METADATA
xll_kit-0.1.1.dist-info/WHEEL
xll_kit-0.1.1.dist-info/RECORD
