Metadata-Version: 2.4
Name: xll-kit
Version: 0.1.1
Summary: xll python
Requires-Python: >=3.10
Requires-Dist: aiomysql>=0.3.2
Requires-Dist: aiosqlite>=0.21.0
Requires-Dist: pydantic-settings>=2.8.0
Requires-Dist: pydantic[email]>=2.10.6
Requires-Dist: pymysql>=1.1.2
Requires-Dist: redis==7.1.0
Requires-Dist: sqlalchemy>=2.0.28
